kg_grafana/__init__.py
kg_grafana/builder.py
kg_grafana/configfile.py
kg_grafana/option.py
kg_grafana/py.typed
kg_grafana/util.py
kg_grafana/tests/__init__.py
kg_grafana/tests/test_builder.py
kg_grafana-0.8.4.dist-info/LICENSE
kg_grafana-0.8.4.dist-info/METADATA
kg_grafana-0.8.4.dist-info/WHEEL
kg_grafana-0.8.4.dist-info/top_level.txt
kg_grafana-0.8.4.dist-info/RECORD
